LICENSE
README.md
moral_keeper_ai/__init__.py
moral_keeper_ai/criteria.py
moral_keeper_ai/llm.py
moral_keeper_ai/moral_keeper_ai.py
moral_keeper_ai/server/server.py
moral_keeper_ai-0.5.0.dist-info/LICENSE
moral_keeper_ai-0.5.0.dist-info/METADATA
moral_keeper_ai-0.5.0.dist-info/WHEEL
moral_keeper_ai-0.5.0.dist-info/entry_points.txt
moral_keeper_ai-0.5.0.dist-info/RECORD
