Metadata-Version: 2.1
Name: moral-keeper-ai
Version: 0.5.0
Summary: 
Home-page: https://github.com/c-3lab/moral-keeper-ai/
License: AGPL-3.0
Author: C3Lab
Author-email: info.c3lab@gmail.com
Requires-Python: >=3.10,<4.0
Classifier: Development Status :: 4 - Beta
Classifier: License :: OSI Approved :: GNU Affero General Public License v3
Classifier: License :: OSI Approved :: GNU Affero General Public License v3 or later (AGPLv3+)
Classifier: Programming Language :: Python :: 3
Classifier: Programming Language :: Python :: 3.10
Classifier: Programming Language :: Python :: 3.11
Classifier: Programming Language :: Python :: 3.12
Classifier: Programming Language :: Python :: 3.13
Requires-Dist: langchain (==0.0.347)
Requires-Dist: langchain-core (==0.0.11)
Requires-Dist: openai (>=1.35.5,<2.0.0)
Requires-Dist: python-dotenv (>=0.20.0,<2.0.0)
Requires-Dist: pyyaml (==6.0.1)
Project-URL: Documentation, https://github.com/c-3lab/moral-keeper-ai/README.md
Project-URL: Repository, https://github.com/c-3lab/moral-keeper-ai/
